{
  "swagger": "2.0",
  "info": {
    "title": "upload.proto",
    "version": "version not set"
  },
  "consumes": [
    "application/json"
  ],
  "produces": [
    "application/json"
  ],
  "paths": {},
  "definitions": {
    "pbStatus": {
      "type": "string",
      "enum": [
        "activated",
        "deactivated"
      ],
      "default": "activated"
    },
    "pbUploadVideoResponse": {
      "type": "object",
      "properties": {
        "video_id": {
          "type": "integer",
          "format": "int32"
        },
        "code": {
          "type": "integer",
          "format": "int32"
        },
        "message": {
          "type": "string"
        }
      }
    },
    "protobufAny": {
      "type": "object",
      "properties": {
        "type_url": {
          "type": "string"
        },
        "value": {
          "type": "string",
          "format": "byte"
        }
      }
    },
    "runtimeError": {
      "type": "object",
      "properties": {
        "error": {
          "type": "string"
        },
        "code": {
          "type": "integer",
          "format": "int32"
        },
        "message": {
          "type": "string"
        },
        "details": {
          "type": "array",
          "items": {
            "$ref": "#/definitions/protobufAny"
          }
        }
      }
    }
  }
}
